LICENSE.txt
MANIFEST.in
README.md
setup.cfg
setup.py
brickscout/__init__.py
brickscout/api.py
brickscout/auth_handler.py
brickscout/cache_handler.py
brickscout/config.py
brickscout/utils.py
brickscout/cache/__init__.py
brickscout/constants/__init__.py
brickscout/constants/constants.py
brickscout/constants/errors.py
brickscout/endpoints/__init__.py
brickscout/endpoints/base.py
brickscout/endpoints/orders.py
brickscout/models/__init__.py
brickscout/models/base.py
brickscout/models/errors.py
brickscout/models/utils.py
python_brickscout_api.egg-info/PKG-INFO
python_brickscout_api.egg-info/SOURCES.txt
python_brickscout_api.egg-info/dependency_links.txt
python_brickscout_api.egg-info/requires.txt
python_brickscout_api.egg-info/top_level.txt