Metadata-Version: 2.1
Name: python-brickscout-api
Version: 1.1.2
Summary: Wrapper for the BrickScout API
Home-page: https://github.com/alexanderlhsglobal/python-brickscout-api
Download-URL: https://github.com/alexanderlhsglobal/python-brickscout-api/archive/refs/tags/1.1.2.tar.gz
Author: Alexander Schillemans
Author-email: alexander.schillemans@hotmail.com
License: GPL-3.0-or-later
Keywords: brickscout,brick,scout,brick scout,lego,api
Classifier: Development Status :: 3 - Alpha
Classifier: Intended Audience :: Developers
Classifier: Topic :: Software Development :: Build Tools
Classifier: License :: OSI Approved :: GNU General Public License v3 or later (GPLv3+)
Classifier: Programming Language :: Python :: 3.10
License-File: LICENSE.txt
